MobileHelperService/__init__.py
MobileHelperService/__main__.py
MobileHelperService/api copy.py
MobileHelperService/api.py
MobileHelperService/client.py
MobileHelperService/collection.py
MobileHelperService/const.py
MobileHelperService/service.py
MobileHelperService/service_api.py
MobileHelperService/tools.py
pih_mio-1.49918.dist-info/METADATA
pih_mio-1.49918.dist-info/WHEEL
pih_mio-1.49918.dist-info/entry_points.txt
pih_mio-1.49918.dist-info/top_level.txt
pih_mio-1.49918.dist-info/RECORD
