Metadata-Version: 2.1
Name: pih-mio
Version: 1.49918
Summary: PIH Mobile helper service package
Home-page: https://pacifichosp.com/
Author: Nikita Karachentsev
Author-email: it@pacifichosp.com
License: MIT
Requires-Dist: ipih
Requires-Dist: pih-mio-content
Requires-Dist: pih-tls
